README.rst
setup.py
immutable/__init__.py
immutable/factories.py
immutable/immutable.py
immutable/tests.py
immutable.egg-info/PKG-INFO
immutable.egg-info/SOURCES.txt
immutable.egg-info/dependency_links.txt
immutable.egg-info/not-zip-safe
immutable.egg-info/top_level.txt